[
  {
    "id": "34f1c7a8-f224-4ce8-9a98-dbfc83289948",
    "name": "Rosie Hills Sr.",
    "phone": "1-783-389-5976 x19695",
    "email": "Elnora_DAmore92@yahoo.com",
    "job": "International Applications Designer"
  },
  {
    "id": "3cc40a28-bc6d-43bc-84f0-b6bdac3c2a3b",
    "name": "Vincent Quigley",
    "phone": "239.713.3479 x2592",
    "email": "Caroline_Bradtke13@gmail.com",
    "job": "Human Infrastructure Facilitator"
  },
  {
    "id": "941edd6f-0634-4f10-b1ca-058757d33e01",
    "name": "Alex Kulas-Berge",
    "phone": "1-336-507-5992 x33930",
    "email": "Quincy_Kuhn95@yahoo.com",
    "job": "Central Integration Developer"
  },
  {
    "id": "aae77148-99bb-41f5-b75c-8c65a858b3c5",
    "name": "Caroline Dach",
    "phone": "(287) 534-3804 x3191",
    "email": "Coty.Hermiston73@hotmail.com",
    "job": "Legacy Solutions Administrator"
  },
  {
    "id": "0075956e-c81a-4cb0-999f-9d5fe879c70f",
    "name": "Carroll McKenzie",
    "phone": "(523) 588-3489 x352",
    "email": "Mariam.Bergstrom29@gmail.com",
    "job": "International Identity Director"
  },
  {
    "id": "5be77e43-f839-4c42-b0f5-2beb1d1683e3",
    "name": "Cory Parker",
    "phone": "839.424.3210 x387",
    "email": "Delmer.Hammes@gmail.com",
    "job": "Senior Tactics Agent"
  },
  {
    "id": "28e252c3-c945-48b3-8f72-4310a0f20f62",
    "name": "Marc Harvey DDS",
    "phone": "395.719.9956",
    "email": "Merritt.Kirlin55@hotmail.com",
    "job": "Lead Branding Facilitator"
  }
]